addition/__init__.py
addition/sum.py
subtraction/__init__.py
subtraction/sub.py
vtslib-2.0.dist-info/METADATA
vtslib-2.0.dist-info/WHEEL
vtslib-2.0.dist-info/top_level.txt
vtslib-2.0.dist-info/RECORD
