Metadata-Version: 2.4
Name: vtslib
Version: 2.0
Summary: My first Python library
Author: VTS
License: MIT
Dynamic: author
Dynamic: license
Dynamic: summary
